{
  "domain": "bof.fire.ca.gov",
  "targetURL": "https://bof.fire.ca.gov/",
  "www": false,
  "active": true,
  "includeInScan": true,
  "title": "Access Denied",
  "lastStatus": 403,
  "finalUrl": "",
  "responseHeaders": {
    "alt-svc": "h3=\":443\"; ma=93600",
    "connection": "close",
    "content-type": "text/html",
    "mime-version": "1.0",
    "server": "AkamaiGHost",
    "x-content-type-options": "nosniff",
    "x-frame-options": "SAMEORIGIN"
  },
  "cloudflare": false,
  "slow": false,
  "hasStatewideAlerts": false,
  "usesStateTemplate": false,
  "hasJQuery": false,
  "googleAnalytics": [],
  "socialLinks": [],
  "linksToCaGov": false,
  "cosmeticTargetURL": null,
  "errorMessage": "HTTP 403",
  "notes": null,
  "goodScan": false
}