{
  "domain": "cdph.ca.gov",
  "targetURL": "https://www.cdph.ca.gov/",
  "www": true,
  "active": true,
  "includeInScan": true,
  "title": "CDPH Home",
  "lastStatus": 200,
  "finalUrl": "",
  "responseHeaders": [
    {
      "name": "content-encoding",
      "value": "gzip"
    },
    {
      "name": "content-type",
      "value": "text/html; charset=utf-8"
    },
    {
      "name": "microsoftsharepointteamservices",
      "value": "16.0.0.10417"
    },
    {
      "name": "server",
      "value": "volt-adc"
    },
    {
      "name": "spiislatency",
      "value": "0"
    },
    {
      "name": "transfer-encoding",
      "value": "chunked"
    },
    {
      "name": "vary",
      "value": "*"
    },
    {
      "name": "x-content-type-options",
      "value": "nosniff"
    },
    {
      "name": "x-frame-options",
      "value": "SAMEORIGIN"
    },
    {
      "name": "x-ms-invokeapp",
      "value": "1; RequireReadOnly"
    },
    {
      "name": "x-sharepointhealthscore",
      "value": "0"
    }
  ],
  "cloudflare": false,
  "slow": false,
  "hasStatewideAlerts": true,
  "usesStateTemplate": false,
  "hasJQuery": true,
  "googleAnalytics": [
    "G-RESPONSIVE",
    "GTM-KVN6ZCB"
  ],
  "socialLinks": [
    "https://instagram.com/capublichealth/",
    "https://www.facebook.com/CAPublicHealth",
    "https://www.linkedin.com/company/california-department-of-public-health",
    "https://www.youtube.com/user/CAPublicHealth",
    "https://twitter.com/CAPublicHealth",
    "https://www.tiktok.com/@capublichealth"
  ],
  "linksToCaGov": true,
  "cosmeticTargetURL": null,
  "errorMessage": null,
  "notes": null,
  "nocache": false
}