{
  "domain": "dublin.ca.gov",
  "targetURL": "https://www.dublin.ca.gov/",
  "www": true,
  "active": true,
  "includeInScan": true,
  "title": "Dublin, CA - Official Website | Official Website",
  "lastStatus": 200,
  "finalUrl": "",
  "responseHeaders": {
    "content-encoding": "gzip",
    "content-type": "text/html; charset=utf-8",
    "p3p": "CP=\"IDC DSP COR ADM DEVi TAIi PSA PSD IVAi IVDi CONi HIS OUR IND CNT\"",
    "x-content-type-options": "nosniff"
  },
  "cloudflare": false,
  "slow": false,
  "hasStatewideAlerts": false,
  "usesStateTemplate": false,
  "hasJQuery": true,
  "googleAnalytics": [
    "G-6REM15SLX9",
    "G-J43R5LMW0E",
    "GTM-K73C5PS"
  ],
  "socialLinks": [
    "https://twitter.com/DublinPIO"
  ],
  "linksToCaGov": false,
  "cosmeticTargetURL": null,
  "errorMessage": null,
  "notes": null,
  "nocache": false
}