{
  "domain": "files.resources.ca.gov",
  "targetURL": "https://files.resources.ca.gov/",
  "www": false,
  "active": true,
  "includeInScan": true,
  "title": "files.resources.ca.gov —  Domain welcome page for",
  "lastStatus": 200,
  "finalUrl": "https://files.resources.ca.gov/",
  "metaGenerator": null,
  "responseHeaders": [
    {
      "name": "accept-ranges",
      "value": "bytes"
    },
    {
      "name": "connection",
      "value": "keep-alive"
    },
    {
      "name": "content-type",
      "value": "text/html"
    },
    {
      "name": "last-modified",
      "value": "Fri, 26 Sep 2025 00:54:36 GMT"
    },
    {
      "name": "server",
      "value": "nginx"
    }
  ],
  "cloudflare": false,
  "slow": false,
  "hasStatewideAlerts": false,
  "usesStateTemplate": false,
  "hasJQuery": false,
  "googleAnalytics": [],
  "socialLinks": [],
  "linksToCaGov": false,
  "cosmeticTargetURL": null,
  "errorMessage": null,
  "notes": null
}