{
  "domain": "ig.dot.ca.gov",
  "targetURL": "https://ig.dot.ca.gov/",
  "www": false,
  "active": true,
  "includeInScan": true,
  "title": "Inspector General - California Department of Transportation | IOAI",
  "lastStatus": 200,
  "finalUrl": "https://ig.dot.ca.gov/",
  "metaGenerator": null,
  "responseHeaders": [
    {
      "name": "accept-ch",
      "value": "Sec-CH-UA-Full-Version-List,Sec-CH-UA-Platform-Version,Sec-CH-UA-Arch,Sec-CH-UA-Model,Sec-CH-UA-Bitness"
    },
    {
      "name": "cache-control",
      "value": "no-cache, no-store"
    },
    {
      "name": "content-type",
      "value": "text/html; charset=utf-8"
    },
    {
      "name": "expires",
      "value": "-1"
    },
    {
      "name": "pragma",
      "value": "no-cache"
    },
    {
      "name": "server-timing",
      "value": "dtSInfo;desc=\"0\", dtRpid;desc=\"694111738\""
    },
    {
      "name": "x-oneagent-js-injection",
      "value": "true"
    },
    {
      "name": "x-ruxit-js-agent",
      "value": "true"
    }
  ],
  "cloudflare": false,
  "slow": false,
  "hasStatewideAlerts": false,
  "usesStateTemplate": false,
  "hasJQuery": false,
  "googleAnalytics": [],
  "socialLinks": [],
  "linksToCaGov": true,
  "cosmeticTargetURL": null,
  "errorMessage": null,
  "notes": null
}