{
  "domain": "ombc.ca.gov",
  "targetURL": "https://www.ombc.ca.gov/",
  "www": true,
  "active": true,
  "includeInScan": true,
  "title": "Welcome To Our Web Site - Osteopathic Medical Board of California",
  "lastStatus": 200,
  "finalUrl": "https://www.ombc.ca.gov/",
  "metaGenerator": null,
  "responseHeaders": [
    {
      "name": "accept-ranges",
      "value": "bytes"
    },
    {
      "name": "access-control-allow-private-network",
      "value": "true"
    },
    {
      "name": "cache-control",
      "value": "max-age=16070400; includeSubdomains; preload"
    },
    {
      "name": "connection",
      "value": "Keep-Alive"
    },
    {
      "name": "content-type",
      "value": "text/html"
    },
    {
      "name": "keep-alive",
      "value": "timeout=5, max=82"
    },
    {
      "name": "referrer-policy",
      "value": "strict-origin-when-cross-origin"
    },
    {
      "name": "strict-transport-security",
      "value": "max-age=16070400; includeSubDomains; preload"
    },
    {
      "name": "transfer-encoding",
      "value": "chunked"
    },
    {
      "name": "x-content-type-options",
      "value": "nosniff"
    },
    {
      "name": "x-frame-options",
      "value": "SAMEORIGIN"
    },
    {
      "name": "x-xss-protection",
      "value": "1; mode=block"
    }
  ],
  "cloudflare": false,
  "slow": false,
  "hasStatewideAlerts": false,
  "usesStateTemplate": false,
  "hasJQuery": false,
  "googleAnalytics": [],
  "socialLinks": [
    "https://m.facebook.com/OsteoBoardCA/",
    "https://twitter.com/OsteoBoardCA/",
    "https://www.linkedin.com/company/osteopathic-medical-board-of-california",
    "https://www.facebook.com/OsteoBoardCA",
    "https://twitter.com/i/flow/login?redirect_after_login=%2FOsteoBoardCA%2F",
    "https://www.linkedin.com/company/osteopathic-medical-board-of-california",
    "https://www.facebook.com/OsteoBoardCA"
  ],
  "linksToCaGov": true,
  "cosmeticTargetURL": null,
  "errorMessage": null,
  "notes": null
}