{
  "domain": "vmb.ca.gov",
  "targetURL": "https://www.vmb.ca.gov/",
  "www": true,
  "active": true,
  "includeInScan": true,
  "title": "Welcome to the California Veterinary Medical Board (VMB)",
  "lastStatus": 200,
  "lastChecked": "2026-01-23T23:08:38.988Z",
  "finalUrl": "https://www.vmb.ca.gov/",
  "metaGenerator": null,
  "responseHeaders": [
    {
      "name": "accept-ranges",
      "value": "bytes"
    },
    {
      "name": "access-control-allow-private-network",
      "value": "true"
    },
    {
      "name": "cache-control",
      "value": "max-age=16070400; includeSubdomains; preload"
    },
    {
      "name": "connection",
      "value": "Keep-Alive"
    },
    {
      "name": "content-type",
      "value": "text/html"
    },
    {
      "name": "date",
      "value": "Fri, 23 Jan 2026 23:08:38 GMT"
    },
    {
      "name": "keep-alive",
      "value": "timeout=5, max=99"
    },
    {
      "name": "referrer-policy",
      "value": "strict-origin-when-cross-origin"
    },
    {
      "name": "set-cookie",
      "value": "TS0118504a=01ed741c22e6fefcaad52e6a8afd69f56eb11bb0e004dfe66b9474ca8b9e2bae10691afc9feb10fb0db5a8fb7cf873dc32175afd12; Path=/; Domain=.www.vmb.ca.gov"
    },
    {
      "name": "strict-transport-security",
      "value": "max-age=16070400; includeSubDomains; preload"
    },
    {
      "name": "transfer-encoding",
      "value": "chunked"
    },
    {
      "name": "x-content-type-options",
      "value": "nosniff"
    },
    {
      "name": "x-frame-options",
      "value": "SAMEORIGIN"
    },
    {
      "name": "x-xss-protection",
      "value": "1; mode=block"
    }
  ],
  "contentSize": 49742,
  "cloudflare": false,
  "slow": false,
  "hasStatewideAlerts": false,
  "usesStateTemplate": false,
  "hasJQuery": false,
  "googleAnalytics": [],
  "socialLinks": [
    "https://twitter.com/vetmedboard",
    "https://www.facebook.com/CA.VetMedBoard/"
  ],
  "linksToCaGov": true,
  "cosmeticTargetURL": null,
  "errorMessage": null,
  "notes": null
}